Metadata-Version: 2.4
Name: adafruit-circuitpython-vcnl4040
Version: 1.2.23
Summary: A CircuitPython library for the VCNL4040 proximity and ambient light sensor.
Author-email: Adafruit Industries <circuitpython@adafruit.com>
License: MIT
Project-URL: Homepage, https://github.com/adafruit/Adafruit_CircuitPython_VCNL4040
Keywords: adafruit,blinka,circuitpython,micropython,vcnl4040,ambient,light,proximity,ir,sensor,hardware
Classifier: Intended Audience :: Developers
Classifier: Topic :: Software Development :: Libraries
Classifier: Topic :: Software Development :: Embedded Systems
Classifier: Topic :: System :: Hardware
Classifier: License :: OSI Approved :: MIT License
Classifier: Programming Language :: Python :: 3
License-File: LICENSE
Requires-Dist: Adafruit-Blinka
Requires-Dist: adafruit-circuitpython-register
Requires-Dist: adafruit-circuitpython-busdevice
Provides-Extra: optional
Dynamic: license-file
